Workbook

Sheet Movies
A1: id | B1: title | C1: genre_ids | D1: release_date | E1: original_language | F1: popularity | G1: vote_average | H1: vote_count | I1: genres | J1: content_type | K1: content_type2
A2: 1169516 | B2: Welcome to the Jungle | C2: [28, 35, 12, 80] | D2: 2026 | E2: hi | F2: 597.0277 | G2: 5.3 | H2: 12 | I2: Action | J2: Movie | K2: Movie
A3: 1169516 | B3: Welcome to the Jungle | C3: [28, 35, 12, 80] | D3: 2026 | E3: hi | F3: 597.0277 | G3: 5.3 | H3: 12 | I3: Comedy | J3: Movie | K3: Movie
A4: 1169516 | B4: Welcome to the Jungle | C4: [28, 35, 12, 80] | D4: 2026 | E4: hi | F4: 597.0277 | G4: 5.3 | H4: 12 | I4: Adventure | J4: Movie | K4: Movie
A5: 1169516 | B5: Welcome to the Jungle | C5: [28, 35, 12, 80] | D5: 2026 | E5: hi | F5: 597.0277 | G5: 5.3 | H5: 12 | I5: Crime | J5: Movie | K5: Movie
A6: 1275779 | B6: Disclosure Day | C6: [878, 53] | D6: 2026 | E6: en | F6: 592.339 | G6: 6.69 | H6: 730 | I6: Science Fiction | J6: Movie | K6: Movie
A7: 1275779 | B7: Disclosure Day | C7: [878, 53] | D7: 2026 | E7: en | F7: 592.339 | G7: 6.69 | H7: 730 | I7: Thriller | J7: Movie | K7: Movie
A8: 1084244 | B8: Toy Story 5 | C8: [16, 10751, 35, 12] | D8: 2026 | E8: en | F8: 555.254 | G8: 7.473 | H8: 374 | I8: Animation | J8: Movie | K8: Movie
A9: 1084244 | B9: Toy Story 5 | C9: [16, 10751, 35, 12] | D9: 2026 | E9: en | F9: 555.254 | G9: 7.473 | H9: 374 | I9: Family | J9: Movie | K9: Movie
A10: 1084244 | B10: Toy Story 5 | C10: [16, 10751, 35, 12] | D10: 2026 | E10: en | F10: 555.254 | G10: 7.473 | H10: 374 | I10: Comedy | J10: Movie | K10: Movie
A11: 1084244 | B11: Toy Story 5 | C11: [16, 10751, 35, 12] | D11: 2026 | E11: en | F11: 555.254 | G11: 7.473 | H11: 374 | I11: Adventure | J11: Movie | K11: Movie
A12: 1083381 | B12: Backrooms | C12: [27, 9648, 878] | D12: 2026 | E12: en | F12: 457.4145 | G12: 6.85 | H12: 791 | I12: Horror | J12: Movie | K12: Movie
A13: 1083381 | B13: Backrooms | C13: [27, 9648, 878] | D13: 2026 | E13: en | F13: 457.4145 | G13: 6.85 | H13: 791 | I13: Mystery | J13: Movie | K13: Movie
... A459: 372058 | B459: Your Name. | C459: [16, 10749, 18] | D459: 2016 | E459: ja | F459: 30.533 | G459: 8.481 | H459: 12652 | I459: Drama | J459: Movie | K459: Movie
A460: 1137129 | B460: Pedro Had a Horse | C460: [] | D460: 2023 | E460: pt | F460: 30.4934 | G460: 8.5 | H460: 2 | J460: Movie | K460: Movie
A461: 1168190 | B461: The Wrecking Crew | C461: [28, 35, 80, 9648] | D461: 2026 | E461: en | F461: 30.4309 | G461: 7.037 | H461: 1102 | I461: Action | J461: Movie | K461: Movie
A462: 1168190 | B462: The Wrecking Crew | C462: [28, 35, 80, 9648] | D462: 2026 | E462: en | F462: 30.4309 | G462: 7.037 | H462: 1102 | I462: Comedy | J462: Movie | K462: Movie
A463: 1168190 | B463: The Wrecking Crew | C463: [28, 35, 80, 9648] | D463: 2026 | E463: en | F463: 30.4309 | G463: 7.037 | H463: 1102 | I463: Crime | J463: Movie | K463: Movie
A464: 1168190 | B464: The Wrecking Crew | C464: [28, 35, 80, 9648] | D464: 2026 | E464: en | F464: 30.4309 | G464: 7.037 | H464: 1102 | I464: Mystery | J464: Movie | K464: Movie
A465: 1022789 | B465: Inside Out 2 | C465: [16, 12, 35, 10751] | D465: 2024 | E465: en | F465: 30.3662 | G465: 7.542 | H465: 6746 | I465: Animation | J465: Movie | K465: Movie
A466: 1022789 | B466: Inside Out 2 | C466: [16, 12, 35, 10751] | D466: 2024 | E466: en | F466: 30.3662 | G466: 7.542 | H466: 6746 | I466: Adventure | J466: Movie | K466: Movie
A467: 1022789 | B467: Inside Out 2 | C467: [16, 12, 35, 10751] | D467: 2024 | E467: en | F467: 30.3662 | G467: 7.542 | H467: 6746 | I467: Comedy | J467: Movie | K467: Movie
A468: 1022789 | B468: Inside Out 2 | C468: [16, 12, 35, 10751] | D468: 2024 | E468: en | F468: 30.3662 | G468: 7.542 | H468: 6746 | I468: Family | J468: Movie | K468: Movie
A469: 1272837 | B469: 28 Years Later: The Bone Temple | C469: [27, 53, 878] | D469: 2026 | E469: en | F469: 30.3279 | G469: 7.12 | H469: 1344 | I469: Horror | J469: Movie | K469: Movie
A470: 1272837 | B470: 28 Years Later: The Bone Temple | C470: [27, 53, 878] | D470: 2026 | E470: en | F470: 30.3279 | G470: 7.12 | H470: 1344 | I470: Thriller | J470: Movie | K470: Movie
A471: 1272837 | B471: 28 Years Later: The Bone Temple | C471: [27, 53, 878] | D471: 2026 | E471: en | F471: 30.3279 | G471: 7.12 | H471: 1344 | I471: Science Fiction | J471: Movie | K471: Movie
A472: 14836 | B472: Coraline | C472: [16, 10751, 14] | D472: 2009 | E472: en | F472: 30.2852 | G472: 7.916 | H472: 9075 | I472: Animation | J472: Movie | K472: Movie
... A1082: 608812 | B1082: Handjob Cabin | C1082: [27, 35] | D1082: 2015 | E1082: en | F1082: 18.6664 | G1082: 7.1 | H1082: 12 | I1082: Comedy | J1082: Movie | K1082: Movie
A1083: 934750 | B1083: Molester Diary: A Man Who Kept Stroking Ass 2 | C1083: [] | D1083: 1995 | E1083: ja | F1083: 18.6532 | G1083: 6 | H1083: 1 | J1083: Movie | K1083: Movie
A1084: 980571 | B1084: Fractured Justice | C1084: [80, 53] | D1084: 2028 | E1084: en | F1084: 18.555 | G1084: 0 | H1084: 0 | I1084: Crime | J1084: Movie | K1084: Movie
A1085: 980571 | B1085: Fractured Justice | C1085: [80, 53] | D1085: 2028 | E1085: en | F1085: 18.555 | G1085: 0 | H1085: 0 | I1085: Thriller | J1085: Movie | K1085: Movie
A1086: 1231940 | B1086: Nice Sister-in-law 6 | C1086: [10749] | D1086: 2023 | E1086: ko | F1086: 18.5462 | G1086: 4 | H1086: 1 | I1086: Romance | J1086: Movie | K1086: Movie
A1087: 278154 | B1087: Ice Age: Collision Course | C1087: [12, 16, 10751, 35, 878] | D1087: 2016 | E1087: en | F1087: 18.5067 | G1087: 6.116 | H1087: 4893 | I1087: Adventure | J1087: Movie | K1087: Movie
A1088: 278154 | B1088: Ice Age: Collision Course | C1088: [12, 16, 10751, 35, 878] | D1088: 2016 | E1088: en | F1088: 18.5067 | G1088: 6.116 | H1088: 4893 | I1088: Animation | J1088: Movie | K1088: Movie
A1089: 278154 | B1089: Ice Age: Collision Course | C1089: [12, 16, 10751, 35, 878] | D1089: 2016 | E1089: en | F1089: 18.5067 | G1089: 6.116 | H1089: 4893 | I1089: Family | J1089: Movie | K1089: Movie
A1090: 278154 | B1090: Ice Age: Collision Course | C1090: [12, 16, 10751, 35, 878] | D1090: 2016 | E1090: en | F1090: 18.5067 | G1090: 6.116 | H1090: 4893 | I1090: Comedy | J1090: Movie | K1090: Movie
A1091: 278154 | B1091: Ice Age: Collision Course | C1091: [12, 16, 10751, 35, 878] | D1091: 2016 | E1091: en | F1091: 18.5067 | G1091: 6.116 | H1091: 4893 | I1091: Science Fiction | J1091: Movie | K1091: Movie
A1092: 122917 | B1092: The Hobbit: The Battle of the Five Armies | C1092: [28, 12, 14] | D1092: 2014 | E1092: en | F1092: 18.5029 | G1092: 7.336 | H1092: 15434 | I1092: Action | J1092: Movie | K1092: Movie
A1093: 122917 | B1093: The Hobbit: The Battle of the Five Armies | C1093: [28, 12, 14] | D1093: 2014 | E1093: en | F1093: 18.5029 | G1093: 7.336 | H1093: 15434 | I1093: Adventure | J1093: Movie | K1093: Movie
A1094: 122917 | B1094: The Hobbit: The Battle of the Five Armies | C1094: [28, 12, 14] | D1094: 2014 | E1094: en | F1094: 18.5029 | G1094: 7.336 | H1094: 15434 | I1094: Fantasy | J1094: Movie | K1094: Movie
A1095: 1716394 | B1095: Дублер | C1095: [18, 35, 53] | D1095: 2026 | E1095: uk | F1095: 18.4954 | G1095: 10 | H1095: 1 | I1095: Drama | J1095: Movie | K1095: Movie
... A1144: 1220522 | B1144: Dacoit | C1144: [28, 10749, 53] | D1144: 2026 | E1144: te | F1144: 18.0597 | G1144: 6.6 | H1144: 5 | I1144: Thriller | J1144: Movie | K1144: Movie
A1145: 630940 | B1145: Jokyoshi Nikki 2 Abakareta Sei | C1145: [] | D1145: 1996 | E1145: ja | F1145: 18.0556 | G1145: 9.3 | H1145: 6 | J1145: Movie | K1145: Movie
A1146: 38757 | B1146: Tangled | C1146: [16, 10751, 12] | D1146: 2010 | E1146: en | F1146: 18.0032 | G1146: 7.613 | H1146: 12446 | I1146: Animation | J1146: Movie | K1146: Movie
A1147: 38757 | B1147: Tangled | C1147: [16, 10751, 12] | D1147: 2010 | E1147: en | F1147: 18.0032 | G1147: 7.613 | H1147: 12446 | I1147: Family | J1147: Movie | K1147: Movie
A1148: 38757 | B1148: Tangled | C1148: [16, 10751, 12] | D1148: 2010 | E1148: en | F1148: 18.0032 | G1148: 7.613 | H1148: 12446 | I1148: Adventure | J1148: Movie | K1148: Movie
A1149: 1175942 | B1149: The Bad Guys 2 | C1149: [10751, 35, 80, 12, 16] | D1149: 2025 | E1149: en | F1149: 17.9447 | G1149: 7.646 | H1149: 806 | I1149: Family | J1149: Movie | K1149: Movie
A1150: 1175942 | B1150: The Bad Guys 2 | C1150: [10751, 35, 80, 12, 16] | D1150: 2025 | E1150: en | F1150: 17.9447 | G1150: 7.646 | H1150: 806 | I1150: Comedy | J1150: Movie | K1150: Movie
A1151: 1175942 | B1151: The Bad Guys 2 | C1151: [10751, 35, 80, 12, 16] | D1151: 2025 | E1151: en | F1151: 17.9447 | G1151: 7.646 | H1151: 806 | I1151: Crime | J1151: Movie | K1151: Movie
A1152: 1175942 | B1152: The Bad Guys 2 | C1152: [10751, 35, 80, 12, 16] | D1152: 2025 | E1152: en | F1152: 17.9447 | G1152: 7.646 | H1152: 806 | I1152: Adventure | J1152: Movie | K1152: Movie
A1153: 1175942 | B1153: The Bad Guys 2 | C1153: [10751, 35, 80, 12, 16] | D1153: 2025 | E1153: en | F1153: 17.9447 | G1153: 7.646 | H1153: 806 | I1153: Animation | J1153: Movie | K1153: Movie
A1154: 123338 | B1154: Sex and Zen III | C1154: [35, 10749, 18] | D1154: 1998 | E1154: cn | F1154: 17.911 | G1154: 6.183 | H1154: 30 | I1154: Comedy | J1154: Movie | K1154: Movie
A1155: 123338 | B1155: Sex and Zen III | C1155: [35, 10749, 18] | D1155: 1998 | E1155: cn | F1155: 17.911 | G1155: 6.183 | H1155: 30 | I1155: Romance | J1155: Movie | K1155: Movie
A1156: 123338 | B1156: Sex and Zen III | C1156: [35, 10749, 18] | D1156: 1998 | E1156: cn | F1156: 17.911 | G1156: 6.183 | H1156: 30 | I1156: Drama | J1156: Movie | K1156: Movie
A1157: 271110 | B1157: Captain America: Civil War | C1157: [12, 28, 878] | D1157: 2016 | E1157: en | F1157: 17.8893 | G1157: 7.449 | H1157: 24108 | I1157: Adventure | J1157: Movie | K1157: Movie
... A1185: 18240 | B1185: The Proposal | C1185: [35, 10749, 18] | D1185: 2009 | E1185: en | F1185: 17.7292 | G1185: 7.171 | H1185: 7582 | I1185: Drama | J1185: Movie | K1185: Movie
A1186: 1409389 | B1186: Dirty Pilgrimage to the West: Broken Volume | C1186: [] | D1186: 1988 | E1186: ja | F1186: 17.6961 | G1186: 6 | H1186: 1 | J1186: Movie | K1186: Movie
A1187: 3933 | B1187: Corpse Bride | C1187: [10749, 14, 16] | D1187: 2005 | E1187: en | F1187: 17.6881 | G1187: 7.592 | H1187: 10239 | I1187: Romance | J1187: Movie | K1187: Movie
A1188: 3933 | B1188: Corpse Bride | C1188: [10749, 14, 16] | D1188: 2005 | E1188: en | F1188: 17.6881 | G1188: 7.592 | H1188: 10239 | I1188: Fantasy | J1188: Movie | K1188: Movie
A1189: 3933 | B1189: Corpse Bride | C1189: [10749, 14, 16] | D1189: 2005 | E1189: en | F1189: 17.6881 | G1189: 7.592 | H1189: 10239 | I1189: Animation | J1189: Movie | K1189: Movie
A1190: 57800 | B1190: Ice Age: Continental Drift | C1190: [16, 35, 12, 10751] | D1190: 2012 | E1190: en | F1190: 17.6794 | G1190: 6.388 | H1190: 8137 | I1190: Animation | J1190: Movie | K1190: Movie
A1191: 57800 | B1191: Ice Age: Continental Drift | C1191: [16, 35, 12, 10751] | D1191: 2012 | E1191: en | F1191: 17.6794 | G1191: 6.388 | H1191: 8137 | I1191: Comedy | J1191: Movie | K1191: Movie
A1192: 57800 | B1192: Ice Age: Continental Drift | C1192: [16, 35, 12, 10751] | D1192: 2012 | E1192: en | F1192: 17.6794 | G1192: 6.388 | H1192: 8137 | I1192: Adventure | J1192: Movie | K1192: Movie
A1193: 57800 | B1193: Ice Age: Continental Drift | C1193: [16, 35, 12, 10751] | D1193: 2012 | E1193: en | F1193: 17.6794 | G1193: 6.388 | H1193: 8137 | I1193: Family | J1193: Movie | K1193: Movie
A1194: 1196067 | B1194: Worldbreaker | C1194: [28, 27, 878] | D1194: 2025 | E1194: en | F1194: 17.6532 | G1194: 6.015 | H1194: 230 | I1194: Action | J1194: Movie | K1194: Movie
A1195: 1196067 | B1195: Worldbreaker | C1195: [28, 27, 878] | D1195: 2025 | E1195: en | F1195: 17.6532 | G1195: 6.015 | H1195: 230 | I1195: Horror | J1195: Movie | K1195: Movie
A1196: 1196067 | B1196: Worldbreaker | C1196: [28, 27, 878] | D1196: 2025 | E1196: en | F1196: 17.6532 | G1196: 6.015 | H1196: 230 | I1196: Science Fiction | J1196: Movie | K1196: Movie
A1197: 49013 | B1197: Cars 2 | C1197: [16, 10751, 12, 35] | D1197: 2011 | E1197: en | F1197: 17.5306 | G1197: 6.182 | H1197: 8513 | I1197: Animation | J1197: Movie | K1197: Movie
A1198: 49013 | B1198: Cars 2 | C1198: [16, 10751, 12, 35] | D1198: 2011 | E1198: en | F1198: 17.5306 | G1198: 6.182 | H1198: 8513 | I1198: Family | J1198: Movie | K1198: Movie
... A1290: 284053 | B1290: Thor: Ragnarok | C1290: [28, 878, 35] | D1290: 2017 | E1290: en | F1290: 16.919 | G1290: 7.6 | H1290: 22085 | I1290: Comedy | J1290: Movie | K1290: Movie
A1291: 1711691 | B1291: BLUMIA | C1291: [27, 53] | E1291: tr | F1291: 16.891 | G1291: 10 | H1291: 1 | I1291: Horror | J1291: Movie | K1291: Movie
A1292: 1711691 | B1292: BLUMIA | C1292: [27, 53] | E1292: tr | F1292: 16.891 | G1292: 10 | H1292: 1 | I1292: Thriller | J1292: Movie | K1292: Movie
A1293: 1514125 | B1293: Saigon Sunset | C1293: [10749, 18] | D1293: 2025 | E1293: ko | F1293: 16.8869 | G1293: 6 | H1293: 1 | I1293: Romance | J1293: Movie | K1293: Movie
A1294: 1514125 | B1294: Saigon Sunset | C1294: [10749, 18] | D1294: 2025 | E1294: ko | F1294: 16.8869 | G1294: 6 | H1294: 1 | I1294: Drama | J1294: Movie | K1294: Movie
A1295: 10997 | B1295: Farewell My Concubine | C1295: [18] | D1295: 1993 | E1295: zh | F1295: 16.8663 | G1295: 7.904 | H1295: 685 | I1295: Drama | J1295: Movie | K1295: Movie
A1296: 1724 | B1296: The Incredible Hulk | C1296: [878, 28, 12] | D1296: 2008 | E1296: en | F1296: 16.8648 | G1296: 6.244 | H1296: 12753 | I1296: Science Fiction | J1296: Movie | K1296: Movie
A1297: 1724 | B1297: The Incredible Hulk | C1297: [878, 28, 12] | D1297: 2008 | E1297: en | F1297: 16.8648 | G1297: 6.244 | H1297: 12753 | I1297: Action | J1297: Movie | K1297: Movie
A1298: 1724 | B1298: The Incredible Hulk | C1298: [878, 28, 12] | D1298: 2008 | E1298: en | F1298: 16.8648 | G1298: 6.244 | H1298: 12753 | I1298: Adventure | J1298: Movie | K1298: Movie
A1299: 38365 | B1299: Grown Ups | C1299: [35] | D1299: 2010 | E1299: en | F1299: 16.8475 | G1299: 6.424 | H1299: 6731 | I1299: Comedy | J1299: Movie | K1299: Movie
A1300: 293660 | B1300: Deadpool | C1300: [28, 12, 35] | D1300: 2016 | E1300: en | F1300: 16.8206 | G1300: 7.624 | H1300: 32843 | I1300: Action | J1300: Movie | K1300: Movie
A1301: 293660 | B1301: Deadpool | C1301: [28, 12, 35] | D1301: 2016 | E1301: en | F1301: 16.8206 | G1301: 7.624 | H1301: 32843 | I1301: Adventure | J1301: Movie | K1301: Movie
A1302: 293660 | B1302: Deadpool | C1302: [28, 12, 35] | D1302: 2016 | E1302: en | F1302: 16.8206 | G1302: 7.624 | H1302: 32843 | I1302: Comedy | J1302: Movie | K1302: Movie
A1303: 321612 | B1303: Beauty and the Beast | C1303: [10751, 14, 10749] | D1303: 2017 | E1303: en | F1303: 16.8041 | G1303: 6.967 | H1303: 16031 | I1303: Family | J1303: Movie | K1303: Movie
A1304: 321612 | B1304: Beauty and the Beast | C1304: [10751, 14, 10749] | D1304: 2017 | E1304: en | F1304: 16.8041 | G1304: 6.967 | H1304: 16031 | I1304: Fantasy | J1304: Movie | K1304: Movie
... A1351: 1252037 | B1351: The Tank | C1351: [10752, 28, 18] | D1351: 2025 | E1351: de | F1351: 16.5463 | G1351: 7.121 | H1351: 446 | I1351: Drama | J1351: Movie | K1351: Movie
A1352: 1480259 | B1352: 太太日記 | C1352: [] | D1352: 1965 | E1352: cn | F1352: 16.5263 | G1352: 0 | H1352: 0 | J1352: Movie | K1352: Movie
A1353: 1711207 | B1353: Rewind | C1353: [53, 9648] | D1353: 2026 | E1353: en | F1353: 16.5148 | G1353: 10 | H1353: 1 | I1353: Thriller | J1353: Movie | K1353: Movie
A1354: 1711207 | B1354: Rewind | C1354: [53, 9648] | D1354: 2026 | E1354: en | F1354: 16.5148 | G1354: 10 | H1354: 1 | I1354: Mystery | J1354: Movie | K1354: Movie
A1355: 50619 | B1355: The Twilight Saga: Breaking Dawn - Part 1 | C1355: [12, 14, 10749] | D1355: 2011 | E1355: en | F1355: 16.4934 | G1355: 6.2 | H1355: 9289 | I1355: Adventure | J1355: Movie | K1355: Movie
A1356: 50619 | B1356: The Twilight Saga: Breaking Dawn - Part 1 | C1356: [12, 14, 10749] | D1356: 2011 | E1356: en | F1356: 16.4934 | G1356: 6.2 | H1356: 9289 | I1356: Fantasy | J1356: Movie | K1356: Movie
A1357: 50619 | B1357: The Twilight Saga: Breaking Dawn - Part 1 | C1357: [12, 14, 10749] | D1357: 2011 | E1357: en | F1357: 16.4934 | G1357: 6.2 | H1357: 9289 | I1357: Romance | J1357: Movie | K1357: Movie
A1358: 1022787 | B1358: Elio | C1358: [16, 12, 878, 10751] | D1358: 2025 | E1358: en | F1358: 16.452 | G1358: 6.906 | H1358: 1027 | I1358: Animation | J1358: Movie | K1358: Movie
A1359: 1022787 | B1359: Elio | C1359: [16, 12, 878, 10751] | D1359: 2025 | E1359: en | F1359: 16.452 | G1359: 6.906 | H1359: 1027 | I1359: Adventure | J1359: Movie | K1359: Movie
A1360: 1022787 | B1360: Elio | C1360: [16, 12, 878, 10751] | D1360: 2025 | E1360: en | F1360: 16.452 | G1360: 6.906 | H1360: 1027 | I1360: Science Fiction | J1360: Movie | K1360: Movie
A1361: 1022787 | B1361: Elio | C1361: [16, 12, 878, 10751] | D1361: 2025 | E1361: en | F1361: 16.452 | G1361: 6.906 | H1361: 1027 | I1361: Family | J1361: Movie | K1361: Movie
A1362: 829560 | B1362: The Next 365 Days | C1362: [10749, 18] | D1362: 2022 | E1362: pl | F1362: 16.445 | G1362: 6.374 | H1362: 1324 | I1362: Romance | J1362: Movie | K1362: Movie
A1363: 829560 | B1363: The Next 365 Days | C1363: [10749, 18] | D1363: 2022 | E1363: pl | F1363: 16.445 | G1363: 6.374 | H1363: 1324 | I1363: Drama | J1363: Movie | K1363: Movie
A1364: 4257 | B1364: Scary Movie 4 | C1364: [35] | D1364: 2006 | E1364: en | F1364: 16.4296 | G1364: 5.494 | H1364: 3636 | I1364: Comedy | J1364: Movie | K1364: Movie
... A1590: 1446056 | B1590: Junior | C1590: [18, 10751] | D1590: 2025 | E1590: te | F1590: 14.9267 | G1590: 4.1 | H1590: 4 | I1590: Family | J1590: Movie | K1590: Movie
A1591: 1553566 | B1591: 杨门女将之八妹游春 | C1591: [] | D1591: 2001 | E1591: zh | F1591: 14.926 | G1591: 0 | H1591: 0 | J1591: Movie | K1591: Movie
...

Sheet TV Shows
A1: id | B1: name | C1: genre_ids | D1: first_air_date | E1: original_language | F1: popularity | G1: vote_average | H1: vote_count | I1: genres | J1: content_type | K1: content_type2
A2: 124364 | B2: FROM | C2: [9648, 18, 10765] | D2: 2022 | E2: en | F2: 872.1045 | G2: 8.509 | H2: 3852 | I2: Mystery | J2: TV Show | K2: TV Show
A3: 124364 | B3: FROM | C3: [9648, 18, 10765] | D3: 2022 | E3: en | F3: 872.1045 | G3: 8.509 | H3: 3852 | I3: Drama | J3: TV Show | K3: TV Show
A4: 124364 | B4: FROM | C4: [9648, 18, 10765] | D4: 2022 | E4: en | F4: 872.1045 | G4: 8.509 | H4: 3852 | I4: Sci-Fi & Fantasy | J4: TV Show | K4: TV Show
A5: 94997 | B5: House of the Dragon | C5: [10765, 18, 10759] | D5: 2022 | E5: en | F5: 592.0857 | G5: 8.352 | H5: 6391 | I5: Sci-Fi & Fantasy | J5: TV Show | K5: TV Show
A6: 94997 | B6: House of the Dragon | C6: [10765, 18, 10759] | D6: 2022 | E6: en | F6: 592.0857 | G6: 8.352 | H6: 6391 | I6: Drama | J6: TV Show | K6: TV Show
A7: 94997 | B7: House of the Dragon | C7: [10765, 18, 10759] | D7: 2022 | E7: en | F7: 592.0857 | G7: 8.352 | H7: 6391 | I7: Action & Adventure | J7: TV Show | K7: TV Show
A8: 4304 | B8: Xplay | C8: [] | D8: 2003 | E8: en | F8: 397.7885 | G8: 8 | H8: 3 | J8: TV Show | K8: TV Show
A9: 2734 | B9: Law & Order: Special Victims Unit | C9: [80, 18, 9648] | D9: 1999 | E9: en | F9: 303.802 | G9: 7.949 | H9: 4259 | I9: Crime | J9: TV Show | K9: TV Show
A10: 2734 | B10: Law & Order: Special Victims Unit | C10: [80, 18, 9648] | D10: 1999 | E10: en | F10: 303.802 | G10: 7.949 | H10: 4259 | I10: Drama | J10: TV Show | K10: TV Show
A11: 2734 | B11: Law & Order: Special Victims Unit | C11: [80, 18, 9648] | D11: 1999 | E11: en | F11: 303.802 | G11: 7.949 | H11: 4259 | I11: Mystery | J11: TV Show | K11: TV Show
A12: 273240 | B12: Off Campus | C12: [18] | D12: 2026 | E12: en | F12: 284.1439 | G12: 8.982 | H12: 588 | I12: Drama | J12: TV Show | K12: TV Show
A13: 13805 | B13: A Girl's Guide to 21st Century Sex | C13: [99] | D13: 2006 | E13: en | F13: 272.7378 | G13: 5.2 | H13: 18 | I13: Documentary | J13: TV Show | K13: TV Show
A14: 82452 | B14: Avatar: The Last Airbender | C14: [10759, 10765, 18, 10751] | D14: 2024 | E14: en | F14: 268.102 | G14: 7.813 | H14: 1164 | I14: Action & Adventure | J14: TV Show | K14: TV Show
A15: 82452 | B15: Avatar: The Last Airbender | C15: [10759, 10765, 18, 10751] | D15: 2024 | E15: en | F15: 268.102 | G15: 7.813 | H15: 1164 | I15: Sci-Fi & Fantasy | J15: TV Show | K15: TV Show
A16: 82452 | B16: Avatar: The Last Airbender | C16: [10759, 10765, 18, 10751] | D16: 2024 | E16: en | F16: 268.102 | G16: 7.813 | H16: 1164 | I16: Drama | J16: TV Show | K16: TV Show
A17: 82452 | B17: Avatar: The Last Airbender | C17: [10759, 10765, 18, 10751] | D17: 2024 | E17: en | F17: 268.102 | G17: 7.813 | H17: 1164 | I17: Family | J17: TV Show | K17: TV Show
A18: 241002 | B18: Adam's Sweet Agony | C18: [16] | D18: 2024 | E18: ja | F18: 265.819 | G18: 6.611 | H18: 36 | I18: Animation | J18: TV Show | K18: TV Show
A19: 299167 | B19: Dutton Ranch | C19: [37, 18] | D19: 2026 | E19: en | F19: 251.4897 | G19: 9.28 | H19: 330 | I19: Western | J19: TV Show | K19: TV Show
A20: 299167 | B20: Dutton Ranch | C20: [37, 18] | D20: 2026 | E20: en | F20: 251.4897 | G20: 9.28 | H20: 330 | I20: Drama | J20: TV Show | K20: TV Show
... A83: 764 | B83: Midsomer Murders | C83: [80, 18, 9648] | D83: 1997 | E83: en | F83: 158.3244 | G83: 7.5 | H83: 357 | I83: Mystery | J83: TV Show | K83: TV Show
A84: 322649 | B84: CHILL CLUB 推介 | C84: [] | D84: 2020 | E84: cn | F84: 157.5474 | G84: 0 | H84: 0 | J84: TV Show | K84: TV Show
A85: 278178 | B85: I Will Find You | C85: [18, 9648, 80] | D85: 2026 | E85: en | F85: 157.4947 | G85: 8.314 | H85: 161 | I85: Drama | J85: TV Show | K85: TV Show
A86: 278178 | B86: I Will Find You | C86: [18, 9648, 80] | D86: 2026 | E86: en | F86: 157.4947 | G86: 8.314 | H86: 161 | I86: Mystery | J86: TV Show | K86: TV Show
A87: 278178 | B87: I Will Find You | C87: [18, 9648, 80] | D87: 2026 | E87: en | F87: 157.4947 | G87: 8.314 | H87: 161 | I87: Crime | J87: TV Show | K87: TV Show
A88: 232393 | B88: 6 Lovers | C88: [16, 35, 18] | D88: 2021 | E88: ja | F88: 154.9241 | G88: 8.3 | H88: 3 | I88: Animation | J88: TV Show | K88: TV Show
A89: 232393 | B89: 6 Lovers | C89: [16, 35, 18] | D89: 2021 | E89: ja | F89: 154.9241 | G89: 8.3 | H89: 3 | I89: Comedy | J89: TV Show | K89: TV Show
A90: 232393 | B90: 6 Lovers | C90: [16, 35, 18] | D90: 2021 | E90: ja | F90: 154.9241 | G90: 8.3 | H90: 3 | I90: Drama | J90: TV Show | K90: TV Show
A91: 1911 | B91: Bones | C91: [80, 18] | D91: 2005 | E91: en | F91: 150.3328 | G91: 8.186 | H91: 3514 | I91: Crime | J91: TV Show | K91: TV Show
A92: 1911 | B92: Bones | C92: [80, 18] | D92: 2005 | E92: en | F92: 150.3328 | G92: 8.186 | H92: 3514 | I92: Drama | J92: TV Show | K92: TV Show
A93: 1408 | B93: House | C93: [18] | D93: 2004 | E93: en | F93: 149.8852 | G93: 8.566 | H93: 7653 | I93: Drama | J93: TV Show | K93: TV Show
A94: 1431 | B94: CSI: Crime Scene Investigation | C94: [80, 18, 9648] | D94: 2000 | E94: en | F94: 149.2834 | G94: 7.6 | H94: 1393 | I94: Crime | J94: TV Show | K94: TV Show
A95: 1431 | B95: CSI: Crime Scene Investigation | C95: [80, 18, 9648] | D95: 2000 | E95: en | F95: 149.2834 | G95: 7.6 | H95: 1393 | I95: Drama | J95: TV Show | K95: TV Show
A96: 1431 | B96: CSI: Crime Scene Investigation | C96: [80, 18, 9648] | D96: 2000 | E96: en | F96: 149.2834 | G96: 7.6 | H96: 1393 | I96: Mystery | J96: TV Show | K96: TV Show
... A587: 87917 | B587: For All Mankind | C587: [18, 10765, 10768] | D587: 2019 | E587: en | F587: 62.4086 | G587: 7.748 | H587: 959 | I587: War & Politics | J587: TV Show | K587: TV Show
A588: 93643 | B588: TMI SHOW | C588: [] | D588: 2019 | E588: ko | F588: 62.3099 | G588: 0 | H588: 0 | J588: TV Show | K588: TV Show
A589: 74428 | B589: Rosario Tijeras (Mexico) | C589: [18, 80] | D589: 2016 | E589: es | F589: 62.2978 | G589: 7.796 | H589: 2009 | I589: Drama | J589: TV Show | K589: TV Show
A590: 74428 | B590: Rosario Tijeras (Mexico) | C590: [18, 80] | D590: 2016 | E590: es | F590: 62.2978 | G590: 7.796 | H590: 2009 | I590: Crime | J590: TV Show | K590: TV Show
A591: 3452 | B591: Frasier | C591: [35, 10751] | D591: 1993 | E591: en | F591: 62.2804 | G591: 7.7 | H591: 889 | I591: Comedy | J591: TV Show | K591: TV Show
A592: 3452 | B592: Frasier | C592: [35, 10751] | D592: 1993 | E592: en | F592: 62.2804 | G592: 7.7 | H592: 889 | I592: Family | J592: TV Show | K592: TV Show
A593: 2593 | B593: Without a Trace | C593: [80, 9648, 10759, 18] | D593: 2002 | E593: en | F593: 62.2594 | G593: 7.242 | H593: 277 | I593: Crime | J593: TV Show | K593: TV Show
A594: 2593 | B594: Without a Trace | C594: [80, 9648, 10759, 18] | D594: 2002 | E594: en | F594: 62.2594 | G594: 7.242 | H594: 277 | I594: Mystery | J594: TV Show | K594: TV Show
A595: 2593 | B595: Without a Trace | C595: [80, 9648, 10759, 18] | D595: 2002 | E595: en | F595: 62.2594 | G595: 7.242 | H595: 277 | I595: Action & Adventure | J595: TV Show | K595: TV Show
A596: 2593 | B596: Without a Trace | C596: [80, 9648, 10759, 18] | D596: 2002 | E596: en | F596: 62.2594 | G596: 7.242 | H596: 277 | I596: Drama | J596: TV Show | K596: TV Show
A597: 2673 | B597: The O.C. | C597: [18] | D597: 2003 | E597: en | F597: 62.0464 | G597: 7.723 | H597: 940 | I597: Drama | J597: TV Show | K597: TV Show
A598: 4546 | B598: Curb Your Enthusiasm | C598: [35] | D598: 2000 | E598: en | F598: 61.9309 | G598: 8 | H598: 934 | I598: Comedy | J598: TV Show | K598: TV Show
A599: 32726 | B599: Bob's Burgers | C599: [16, 35] | D599: 2011 | E599: en | F599: 61.6736 | G599: 7.841 | H599: 1094 | I599: Animation | J599: TV Show | K599: TV Show
A600: 32726 | B600: Bob's Burgers | C600: [16, 35] | D600: 2011 | E600: en | F600: 61.6736 | G600: 7.841 | H600: 1094 | I600: Comedy | J600: TV Show | K600: TV Show
... A732: 78501 | B732: Sweet Punishment: I'm the Guard's Personal Pet | C732: [16] | D732: 2018 | E732: ja | F732: 55.2578 | G732: 7.214 | H732: 14 | I732: Animation | J732: TV Show | K732: TV Show
A733: 323882 | B733: X调查 | C733: [] | D733: 2019 | E733: zh | F733: 55.1693 | G733: 0 | H733: 0 | J733: TV Show | K733: TV Show
A734: 119051 | B734: Wednesday | C734: [10765, 9648, 35] | D734: 2022 | E734: en | F734: 55.138 | G734: 8.344 | H734: 10596 | I734: Sci-Fi & Fantasy | J734: TV Show | K734: TV Show
A735: 119051 | B735: Wednesday | C735: [10765, 9648, 35] | D735: 2022 | E735: en | F735: 55.138 | G735: 8.344 | H735: 10596 | I735: Mystery | J735: TV Show | K735: TV Show
A736: 119051 | B736: Wednesday | C736: [10765, 9648, 35] | D736: 2022 | E736: en | F736: 55.138 | G736: 8.344 | H736: 10596 | I736: Comedy | J736: TV Show | K736: TV Show
A737: 236338 | B737: Gushing Over Magical Girls | C737: [16, 10765, 35] | D737: 2024 | E737: ja | F737: 55.0304 | G737: 8.216 | H737: 109 | I737: Animation | J737: TV Show | K737: TV Show
A738: 236338 | B738: Gushing Over Magical Girls | C738: [16, 10765, 35] | D738: 2024 | E738: ja | F738: 55.0304 | G738: 8.216 | H738: 109 | I738: Sci-Fi & Fantasy | J738: TV Show | K738: TV Show
A739: 236338 | B739: Gushing Over Magical Girls | C739: [16, 10765, 35] | D739: 2024 | E739: ja | F739: 55.0304 | G739: 8.216 | H739: 109 | I739: Comedy | J739: TV Show | K739: TV Show
A740: 95480 | B740: Slow Horses | C740: [80, 18, 35] | D740: 2022 | E740: en | F740: 54.8362 | G740: 8.005 | H740: 869 | I740: Crime | J740: TV Show | K740: TV Show
A741: 95480 | B741: Slow Horses | C741: [80, 18, 35] | D741: 2022 | E741: en | F741: 54.8362 | G741: 8.005 | H741: 869 | I741: Drama | J741: TV Show | K741: TV Show
A742: 95480 | B742: Slow Horses | C742: [80, 18, 35] | D742: 2022 | E742: en | F742: 54.8362 | G742: 8.005 | H742: 869 | I742: Comedy | J742: TV Show | K742: TV Show
A743: 69050 | B743: Riverdale | C743: [80, 18, 9648] | D743: 2017 | E743: en | F743: 54.7214 | G743: 8.406 | H743: 13733 | I743: Crime | J743: TV Show | K743: TV Show
A744: 69050 | B744: Riverdale | C744: [80, 18, 9648] | D744: 2017 | E744: en | F744: 54.7214 | G744: 8.406 | H744: 13733 | I744: Drama | J744: TV Show | K744: TV Show
A745: 69050 | B745: Riverdale | C745: [80, 18, 9648] | D745: 2017 | E745: en | F745: 54.7214 | G745: 8.406 | H745: 13733 | I745: Mystery | J745: TV Show | K745: TV Show
... A806: 262838 | B806: India's Got Latent | C806: [10764, 35] | D806: 2024 | E806: hi | F806: 52.2713 | G806: 8.75 | H806: 8 | I806: Comedy | J806: TV Show | K806: TV Show
A807: 71932 | B807: AVN Awards | C807: [10764] | E807: en | F807: 52.2516 | G807: 5.852 | H807: 27 | I807: Reality | J807: TV Show | K807: TV Show
A808: 72071 | B808: The Chi | C808: [18] | D808: 2018 | E808: en | F808: 52.2127 | G808: 7.868 | H808: 216 | I808: Drama | J808: TV Show | K808: TV Show
A809: 113962 | B809: Lioness | C809: [18, 10768] | D809: 2023 | E809: en | F809: 52.1298 | G809: 7.991 | H809: 1210 | I809: Drama | J809: TV Show | K809: TV Show
A810: 113962 | B810: Lioness | C810: [18, 10768] | D810: 2023 | E810: en | F810: 52.1298 | G810: 7.991 | H810: 1210 | I810: War & Politics | J810: TV Show | K810: TV Show
A811: 14658 | B811: Survivor | C811: [10764] | D811: 2000 | E811: en | F811: 51.9751 | G811: 7.285 | H811: 434 | I811: Reality | J811: TV Show | K811: TV Show
A812: 79481 | B812: Fights Break Sphere | C812: [16, 10759, 10765] | D812: 2017 | E812: zh | F812: 51.9446 | G812: 8 | H812: 59 | I812: Animation | J812: TV Show | K812: TV Show
A813: 79481 | B813: Fights Break Sphere | C813: [16, 10759, 10765] | D813: 2017 | E813: zh | F813: 51.9446 | G813: 8 | H813: 59 | I813: Action & Adventure | J813: TV Show | K813: TV Show
A814: 79481 | B814: Fights Break Sphere | C814: [16, 10759, 10765] | D814: 2017 | E814: zh | F814: 51.9446 | G814: 8 | H814: 59 | I814: Sci-Fi & Fantasy | J814: TV Show | K814: TV Show
A815: 46195 | B815: Monogatari | C815: [16, 35, 18, 9648] | D815: 2009 | E815: ja | F815: 51.8213 | G815: 8.1 | H815: 522 | I815: Animation | J815: TV Show | K815: TV Show
A816: 46195 | B816: Monogatari | C816: [16, 35, 18, 9648] | D816: 2009 | E816: ja | F816: 51.8213 | G816: 8.1 | H816: 522 | I816: Comedy | J816: TV Show | K816: TV Show
A817: 46195 | B817: Monogatari | C817: [16, 35, 18, 9648] | D817: 2009 | E817: ja | F817: 51.8213 | G817: 8.1 | H817: 522 | I817: Drama | J817: TV Show | K817: TV Show
A818: 46195 | B818: Monogatari | C818: [16, 35, 18, 9648] | D818: 2009 | E818: ja | F818: 51.8213 | G818: 8.1 | H818: 522 | I818: Mystery | J818: TV Show | K818: TV Show
A819: 95057 | B819: Superman & Lois | C819: [18, 10765] | D819: 2021 | E819: en | F819: 51.8185 | G819: 8.061 | H819: 2705 | I819: Drama | J819: TV Show | K819: TV Show
... A850: 14610 | B850: Secret Lives | C850: [10766, 18] | D850: 1999 | E850: fi | F850: 50.5588 | G850: 4.217 | H850: 23 | I850: Drama | J850: TV Show | K850: TV Show
A851: 36978 | B851: Badass | C851: [10764] | E851: en | F851: 50.3132 | G851: 3 | H851: 3 | I851: Reality | J851: TV Show | K851: TV Show
A852: 63333 | B852: The Last Kingdom | C852: [10759, 18, 10768] | D852: 2015 | E852: en | F852: 50.2018 | G852: 8.26 | H852: 1974 | I852: Action & Adventure | J852: TV Show | K852: TV Show
A853: 63333 | B853: The Last Kingdom | C853: [10759, 18, 10768] | D853: 2015 | E853: en | F853: 50.2018 | G853: 8.26 | H853: 1974 | I853: Drama | J853: TV Show | K853: TV Show
A854: 63333 | B854: The Last Kingdom | C854: [10759, 18, 10768] | D854: 2015 | E854: en | F854: 50.2018 | G854: 8.26 | H854: 1974 | I854: War & Politics | J854: TV Show | K854: TV Show
A855: 90521 | B855: Love Island USA | C855: [10764] | D855: 2019 | E855: en | F855: 50.1546 | G855: 7 | H855: 175 | I855: Reality | J855: TV Show | K855: TV Show
A856: 204746 | B856: The Jennifer Hudson Show | C856: [10767] | D856: 2022 | E856: en | F856: 50.1509 | G856: 5.578 | H856: 32 | I856: Talk | J856: TV Show | K856: TV Show
A857: 1920 | B857: Twin Peaks | C857: [18, 9648] | D857: 1990 | E857: en | F857: 49.9486 | G857: 8.34 | H857: 2601 | I857: Drama | J857: TV Show | K857: TV Show
A858: 1920 | B858: Twin Peaks | C858: [18, 9648] | D858: 1990 | E858: en | F858: 49.9486 | G858: 8.34 | H858: 2601 | I858: Mystery | J858: TV Show | K858: TV Show
A859: 2912 | B859: Jeopardy! | C859: [10764, 10751] | D859: 1984 | E859: en | F859: 49.8991 | G859: 6.896 | H859: 159 | I859: Reality | J859: TV Show | K859: TV Show
A860: 2912 | B860: Jeopardy! | C860: [10764, 10751] | D860: 1984 | E860: en | F860: 49.8991 | G860: 6.896 | H860: 159 | I860: Family | J860: TV Show | K860: TV Show
A861: 125364 | B861: Palang Tod | C861: [18] | D861: 2020 | E861: hi | F861: 49.8647 | G861: 1 | H861: 2 | I861: Drama | J861: TV Show | K861: TV Show
A862: 4384 | B862: Frontline | C862: [99, 10763] | D862: 1983 | E862: en | F862: 49.7431 | G862: 6.6 | H862: 57 | I862: Documentary | J862: TV Show | K862: TV Show
A863: 4384 | B863: Frontline | C863: [99, 10763] | D863: 1983 | E863: en | F863: 49.7431 | G863: 6.6 | H863: 57 | I863: News | J863: TV Show | K863: TV Show
... A928: 4582 | B928: Ironside | C928: [80, 18, 9648] | D928: 1967 | E928: en | F928: 47.8622 | G928: 6.857 | H928: 70 | I928: Mystery | J928: TV Show | K928: TV Show
A929: 324723 | B929: PMQ Questions | C929: [] | D929: 1966 | E929: en | F929: 47.7289 | G929: 0 | H929: 0 | J929: TV Show | K929: TV Show
A930: 4515 | B930: Lois & Clark: The New Adventures of Superman | C930: [10759, 18, 10765, 35] | D930: 1993 | E930: en | F930: 47.6585 | G930: 6.931 | H930: 495 | I930: Action & Adventure | J930: TV Show | K930: TV Show
A931: 4515 | B931: Lois & Clark: The New Adventures of Superman | C931: [10759, 18, 10765, 35] | D931: 1993 | E931: en | F931: 47.6585 | G931: 6.931 | H931: 495 | I931: Drama | J931: TV Show | K931: TV Show
A932: 4515 | B932: Lois & Clark: The New Adventures of Superman | C932: [10759, 18, 10765, 35] | D932: 1993 | E932: en | F932: 47.6585 | G932: 6.931 | H932: 495 | I932: Sci-Fi & Fantasy | J932: TV Show | K932: TV Show
A933: 4515 | B933: Lois & Clark: The New Adventures of Superman | C933: [10759, 18, 10765, 35] | D933: 1993 | E933: en | F933: 47.6585 | G933: 6.931 | H933: 495 | I933: Comedy | J933: TV Show | K933: TV Show
A934: 60797 | B934: Scorpion | C934: [10759, 18, 80] | D934: 2014 | E934: en | F934: 47.6521 | G934: 8.206 | H934: 4153 | I934: Action & Adventure | J934: TV Show | K934: TV Show
A935: 60797 | B935: Scorpion | C935: [10759, 18, 80] | D935: 2014 | E935: en | F935: 47.6521 | G935: 8.206 | H935: 4153 | I935: Drama | J935: TV Show | K935: TV Show
A936: 60797 | B936: Scorpion | C936: [10759, 18, 80] | D936: 2014 | E936: en | F936: 47.6521 | G936: 8.206 | H936: 4153 | I936: Crime | J936: TV Show | K936: TV Show
A937: 33765 | B937: My Little Pony: Friendship Is Magic | C937: [16, 35, 10765, 10762] | D937: 2010 | E937: en | F937: 47.5909 | G937: 8.2 | H937: 740 | I937: Animation | J937: TV Show | K937: TV Show
...

Sheet Genre Lookup
A1: genre_id | B1: genre_name
A2: 28 | B2: Action
A3: 12 | B3: Adventure
A4: 16 | B4: Animation
A5: 35 | B5: Comedy
A6: 80 | B6: Crime
A7: 99 | B7: Documentary
A8: 18 | B8: Drama
A9: 10751 | B9: Family
A10: 14 | B10: Fantasy
A11: 36 | B11: History
A12: 27 | B12: Horror
A13: 10402 | B13: Music
... A28: 10768 | B28: War & Politics

Sheet Analysis
A1: Row Labels | B1: Avg popularity
A2: Music | B2: 17.892927
A3: Horror | B3: 17.515186
A4: Science Fiction | B4: 17.319258
A5: Adventure | B5: 17.262762
A6: Animation | B6: 16.792334
A7: Mystery | B7: 16.738171
A8: Crime | B8: 16.390328
A9: Family | B9: 16.292502
A10: Comedy | B10: 16.241757
A11: Action | B11: 15.736196
A12: Thriller | B12: 15.56119
A13: Fantasy | B13: 14.787634
... A20: Grand Total | B20: 15.649439
A22: Row Labels | B22: Avg Vote Score
A23: Western | B23: 6.91525
A24: War | B24: 6.8866164
A25: History | B25: 6.7772708
A26: Music | B26: 6.7212333
A27: Animation | B27: 6.7191935
A28: Adventure | B28: 6.6174399
A29: Fantasy | B29: 6.5816904
A30: Science Fiction | B30: 6.5513539
A31: Action | B31: 6.5437281
A32: Family | B32: 6.5309556
A33: Crime | B33: 6.5208382
A34: Drama | B34: 6.4999482
... A42: Grand Total | B42: 6.4910984
A45: Row Labels | B45: Unique Titles
A46: 1878 | B46: 2
A47: 1892 | B47: 1
A48: 1893 | B48: 2
A49: 1895 | B49: 5
A50: 1896 | B50: 4
A51: 1897 | B51: 2
A52: 1898 | B52: 1
A53: 1899 | B53: 2
A54: 1900 | B54: 2
A55: 1901 | B55: 1
A56: 1906 | B56: 1
A57: 1910 | B57: 1
... A145: 2026 | B145: 351
A146: Grand Total | B146: 2626
A150: Row Labels | B150: Title Count | C150: % Share
A151: en | B151: 1941 | C151: 0.71702992
A152: ko | B152: 114 | C152: 0.04211304
A153: ja | B153: 112 | C153: 0.041374215
A154: fr | B154: 88 | C154: 0.032508312
A155: es | B155: 68 | C155: 0.025120059
A156: zh | B156: 62 | C156: 0.022903583
A157: it | B157: 42 | C157: 0.015515331
A158: cn | B158: 36 | C158: 0.013298855
A159: tl | B159: 35 | C159: 0.012929442
A160: hi | B160: 34 | C160: 0.01256003
A161: pt | B161: 19 | C161: 0.00701884
A162: de | B162: 15 | C162: 0.0055411895
... A201: Grand Total | B201: 2707 | C201: 1
A204: Average of popularity | B204: Column Labels
A205: Row Labels | B205: 2021 | C205: 2022 | D205: 2023 | E205: 2024 | F205: 2025 | G205: Grand Total
A206: Action | B206: 13.746105 | C206: 11.920704 | D206: 11.061141 | E206: 11.110424 | F206: 16.24041 | G206: 13.284629
A207: Adventure | B207: 13.876905 | C207: 11.67165 | D207: 12.550509 | E207: 13.703966 | F207: 21.329836 | G207: 15.205321
A208: Animation | B208: 9.7495 | C208: 11.331917 | D208: 11.386292 | E208: 13.618291 | F208: 21.21755 | G208: 14.695351
A209: Comedy | B209: 9.6822706 | C209: 11.294429 | D209: 10.30082 | E209: 13.138071 | F209: 14.112721 | G209: 12.194143
A210: Crime | B210: 12.009583 | C210: 13.185287 | D210: 24.98128 | E210: 8.36976 | F210: 15.205179 | G210: 14.568624
A211: Documentary | B211: 7.0359 | C211: 11.3296 | D211: 34.1645 | E211: 7.6429 | F211: 21.176067 | G211: 16.262256
A212: Drama | B212: 12.307033 | C212: 11.0938 | D212: 10.91231 | E212: 18.294124 | F212: 12.755115 | G212: 13.555183
A213: Family | B213: 9.37888 | C213: 11.946955 | D213: 10.064409 | E213: 15.753961 | F213: 18.056052 | G213: 14.065665
A214: Fantasy | B214: 12.779833 | C214: 11.113254 | D214: 11.2081 | E214: 10.8433 | F214: 21.59014 | G214: 15.214874
A215: History | B215: 6.65725 | C215: 8.91875 | D215: 12.6504 | E215: 8.9213 | F215: 12.314811 | G215: 11.1949
A216: Horror | B216: 7.4948889 | C216: 8.78325 | D216: 10.749408 | E216: 14.482292 | F216: 13.915512 | G216: 12.559255
A217: Music | B217: 10.6799 | C217: 8.3281 | D217: 7.5188 | E217: 10.423475 | F217: 11.814014 | G217: 10.620425
... A221: Thriller | B221: 10.482986 | C221: 11.847344 | D221: 19.531035 | E221: 10.410307 | F221: 13.834876 | G221: 13.407434
A222: TV Movie | B222: 18.4241 | C222: 14.96625 | D222: 6.7401 | F222: 49.2597 | G222: 20.87128
A223: War | C223: 8.6671 | D223: 7.2593 | E223: 10.867333 | F223: 10.673271 | G223: 9.94055
A224: Western | B224: 6.6737 | C224: 9.1101 | F224: 6.645 | G224: 7.4762667
A225: Grand Total | B225: 11.868979 | C225: 11.395518 | D225: 12.528648 | E225: 14.211048 | F225: 15.906738 | G225: 13.90863
A230: Genre | B230: Avg Popularity | C230: Avg Vote Score | D230: Above Median Popularity? | E230: Above Median Vote? | F230: Sweet Spot?
A231: Action | B231: =AVERAGEIF(Movies!I:I,A231,Movies!F:F) -> 15.736196 | C231: =IFERROR(AVERAGEIF(Movies!I:I,A231,Movies!G:G),0) -> 6.5437281 | D231: =IF(B231>$F$252,"YES","NO") -> NO | E231: =IF(C231>$F$253,"YES","NO") -> YES | F231: =IF(AND(D231="YES",E231="YES"),"⭐ SWEET SPOT","")
A232: Adventure | B232: =AVERAGEIF(Movies!I:I,A232,Movies!F:F) -> 17.262762 | C232: =IFERROR(AVERAGEIF(Movies!I:I,A232,Movies!G:G),0) -> 6.6174399 | D232: =IF(B232>$F$252,"YES","NO") -> YES | E232: =IF(C232>$F$253,"YES","NO") -> YES | F232: =IF(AND(D232="YES",E232="YES"),"⭐ SWEET SPOT","") -> ⭐ SWEET SPOT
A233: Animation | B233: =AVERAGEIF(Movies!I:I,A233,Movies!F:F) -> 16.792334 | C233: =IFERROR(AVERAGEIF(Movies!I:I,A233,Movies!G:G),0) -> 6.7191935 | D233: =IF(B233>$F$252,"YES","NO") -> YES | E233: =IF(C233>$F$253,"YES","NO") -> YES | F233: =IF(AND(D233="YES",E233="YES"),"⭐ SWEET SPOT","") -> ⭐ SWEET SPOT
A234: Comedy | B234: =AVERAGEIF(Movies!I:I,A234,Movies!F:F) -> 16.241757 | C234: =IFERROR(AVERAGEIF(Movies!I:I,A234,Movies!G:G),0) -> 6.457177 | D234: =IF(B234>$F$252,"YES","NO") -> YES | E234: =IF(C234>$F$253,"YES","NO") -> NO | F234: =IF(AND(D234="YES",E234="YES"),"⭐ SWEET SPOT","")
A235: Crime | B235: =AVERAGEIF(Movies!I:I,A235,Movies!F:F) -> 16.390328 | C235: =IFERROR(AVERAGEIF(Movies!I:I,A235,Movies!G:G),0) -> 6.5208382 | D235: =IF(B235>$F$252,"YES","NO") -> YES | E235: =IF(C235>$F$253,"YES","NO") -> NO | F235: =IF(AND(D235="YES",E235="YES"),"⭐ SWEET SPOT","")
A236: Documentary | B236: =IFERROR(AVERAGEIF(Movies!I:I,A236,Movies!F:F),0) -> 11.515766 | C236: =IFERROR(AVERAGEIF(Movies!I:I,A236,Movies!G:G),0) -> 6.1195909 | D236: =IF(B236>$F$252,"YES","NO") -> NO | E236: =IF(C236>$F$253,"YES","NO") -> NO | F236: =IF(AND(D236="YES",E236="YES"),"⭐ SWEET SPOT","")
A237: Drama | B237: =AVERAGEIF(Movies!I:I,A237,Movies!F:F) -> 13.361679 | C237: =IFERROR(AVERAGEIF(Movies!I:I,A237,Movies!G:G),0) -> 6.4999482 | D237: =IF(B237>$F$252,"YES","NO") -> NO | E237: =IF(C237>$F$253,"YES","NO") -> NO | F237: =IF(AND(D237="YES",E237="YES"),"⭐ SWEET SPOT","")
A238: Family | B238: =AVERAGEIF(Movies!I:I,A238,Movies!F:F) -> 16.292502 | C238: =IFERROR(AVERAGEIF(Movies!I:I,A238,Movies!G:G),0) -> 6.5309556 | D238: =IF(B238>$F$252,"YES","NO") -> YES | E238: =IF(C238>$F$253,"YES","NO") -> NO | F238: =IF(AND(D238="YES",E238="YES"),"⭐ SWEET SPOT","")
A239: Fantasy | B239: =AVERAGEIF(Movies!I:I,A239,Movies!F:F) -> 14.787634 | C239: =IFERROR(AVERAGEIF(Movies!I:I,A239,Movies!G:G),0) -> 6.5816904 | D239: =IF(B239>$F$252,"YES","NO") -> NO | E239: =IF(C239>$F$253,"YES","NO") -> YES | F239: =IF(AND(D239="YES",E239="YES"),"⭐ SWEET SPOT","")
A240: History | B240: =AVERAGEIF(Movies!I:I,A240,Movies!F:F) -> 11.922028 | C240: =IFERROR(AVERAGEIF(Movies!I:I,A240,Movies!G:G),0) -> 6.7772708 | D240: =IF(B240>$F$252,"YES","NO") -> NO | E240: =IF(C240>$F$253,"YES","NO") -> YES | F240: =IF(AND(D240="YES",E240="YES"),"⭐ SWEET SPOT","")
A241: Horror | B241: =AVERAGEIF(Movies!I:I,A241,Movies!F:F) -> 17.515186 | C241: =IFERROR(AVERAGEIF(Movies!I:I,A241,Movies!G:G),0) -> 6.1432259 | D241: =IF(B241>$F$252,"YES","NO") -> YES | E241: =IF(C241>$F$253,"YES","NO") -> NO | F241: =IF(AND(D241="YES",E241="YES"),"⭐ SWEET SPOT","")
A242: Music | B242: =AVERAGEIF(Movies!I:I,A242,Movies!F:F) -> 17.892927 | C242: =IFERROR(AVERAGEIF(Movies!I:I,A242,Movies!G:G),0) -> 6.7212333 | D242: =IF(B242>$F$252,"YES","NO") -> YES | E242: =IF(C242>$F$253,"YES","NO") -> YES | F242: =IF(AND(D242="YES",E242="YES"),"⭐ SWEET SPOT","") -> ⭐ SWEET SPOT
A243: Mystery | B243: =AVERAGEIF(Movies!I:I,A243,Movies!F:F) -> 16.738171 | C243: =IFERROR(AVERAGEIF(Movies!I:I,A243,Movies!G:G),0) -> 6.4381275 | D243: =IF(B243>$F$252,"YES","NO") -> YES | E243: =IF(C243>$F$253,"YES","NO") -> NO | F243: =IF(AND(D243="YES",E243="YES"),"⭐ SWEET SPOT","")
A244: Romance | B244: =AVERAGEIF(Movies!I:I,A244,Movies!F:F) -> 14.479205 | C244: =IFERROR(AVERAGEIF(Movies!I:I,A244,Movies!G:G),0) -> 6.3331828 | D244: =IF(B244>$F$252,"YES","NO") -> NO | E244: =IF(C244>$F$253,"YES","NO") -> NO | F244: =IF(AND(D244="YES",E244="YES"),"⭐ SWEET SPOT","")
A245: Science Fiction | B245: =AVERAGEIF(Movies!I:I,A245,Movies!F:F) -> 17.319258 | C245: =IFERROR(AVERAGEIF(Movies!I:I,A245,Movies!G:G),0) -> 6.5513539 | D245: =IF(B245>$F$252,"YES","NO") -> YES | E245: =IF(C245>$F$253,"YES","NO") -> YES | F245: =IF(AND(D245="YES",E245="YES"),"⭐ SWEET SPOT","") -> ⭐ SWEET SPOT
A246: Thriller | B246: =AVERAGEIF(Movies!I:I,A246,Movies!F:F) -> 15.56119 | C246: =IFERROR(AVERAGEIF(Movies!I:I,A246,Movies!G:G),0) -> 6.362 | D246: =IF(B246>$F$252,"YES","NO") -> NO | E246: =IF(C246>$F$253,"YES","NO") -> NO | F246: =IF(AND(D246="YES",E246="YES"),"⭐ SWEET SPOT","")
A247: TV Movie | B247: =AVERAGEIF(Movies!I:I,A247,Movies!F:F) -> 14.006929 | C247: =IFERROR(AVERAGEIF(Movies!I:I,A247,Movies!G:G),0) -> 5.07925 | D247: =IF(B247>$F$252,"YES","NO") -> NO | E247: =IF(C247>$F$253,"YES","NO") -> NO | F247: =IF(AND(D247="YES",E247="YES"),"⭐ SWEET SPOT","")
A248: War | B248: =AVERAGEIF(Movies!I:I,A248,Movies!F:F) -> 11.089319 | C248: =IFERROR(AVERAGEIF(Movies!I:I,A248,Movies!G:G),0) -> 6.8866164 | D248: =IF(B248>$F$252,"YES","NO") -> NO | E248: =IF(C248>$F$253,"YES","NO") -> YES | F248: =IF(AND(D248="YES",E248="YES"),"⭐ SWEET SPOT","")
A249: Western | B249: =AVERAGEIF(Movies!I:I,A249,Movies!F:F) -> 9.9692611 | C249: =IFERROR(AVERAGEIF(Movies!I:I,A249,Movies!G:G),0) -> 6.91525 | D249: =IF(B249>$F$252,"YES","NO") -> NO | E249: =IF(C249>$F$253,"YES","NO") -> YES | F249: =IF(AND(D249="YES",E249="YES"),"⭐ SWEET SPOT","")
E252: Median Popularity: | F252: =MEDIAN(B231:B249) -> 15.736196
E253: Median Vote Score: | F253: =MEDIAN(C231:C249) -> 6.5309556
A258: Avg Popularity | B258: Column Labels
A259: Row Labels | B259: Movie | C259: TV Show | D259: Grand Total
...
